cocotb_mips32/__init__.py
cocotb_mips32/cli.py
cocotb_mips32/processor_test.py
cocotb_mips32/utils/__init__.py
cocotb_mips32/utils/compiling.py
cocotb_mips32-0.5.10.dist-info/LICENSE
cocotb_mips32-0.5.10.dist-info/METADATA
cocotb_mips32-0.5.10.dist-info/WHEEL
cocotb_mips32-0.5.10.dist-info/entry_points.txt
cocotb_mips32-0.5.10.dist-info/top_level.txt
cocotb_mips32-0.5.10.dist-info/RECORD
