Metadata-Version: 2.1
Name: cocotb-mips32
Version: 0.5.10
Summary: A MIPS32 testbench in Python based on cocotb
Home-page: UNKNOWN
Author: Daniel Perdices
Author-email: <daniel.perdices@uam.es>
License: UNKNOWN
Platform: UNKNOWN
License-File: LICENSE
Requires-Dist: cocotb
Requires-Dist: docker
